{
  "timestamp": "20250828_092338",
  "dockerfile_path": "envgym/envgym.dockerfile",
  "image_name": "envgym_test_1756373010",
  "build": {
    "success": true,
    "stdout": "",
    "stderr": "#0 building with \"default\" instance using docker driver\n\n#1 [internal] load build definition from envgym.dockerfile\n#1 transferring dockerfile: 565B done\n#1 DONE 0.0s\n\n#2 [internal] load metadata for docker.io/library/node:14-alpine\n#2 DONE 0.1s\n\n#3 [internal] load .dockerignore\n#3 transferring context: 2B done\n#3 DONE 0.0s\n\n#4 [1/7] FROM docker.io/library/node:14-alpine@sha256:434215b487a329c9e867202ff89e704d3a75e554822e07f3e0c0f9e606121b33\n#4 DONE 0.0s\n\n#5 [internal] load build context\n#5 transferring context: 236.95kB 0.0s done\n#5 DONE 0.0s\n\n#6 [2/7] WORKDIR /home/cc/EnvGym/data/iamkun_dayjs\n#6 CACHED\n\n#7 [5/7] COPY package-lock.json .\n#7 CACHED\n\n#8 [3/7] RUN apk update &&     apk add --no-cache     git     chromium     bash\n#8 CACHED\n\n#9 [4/7] COPY package.json .\n#9 CACHED\n\n#10 [6/7] RUN npm install &&     npm install -g     @babel/core     @babel/cli     @babel/node     jest     eslint     prettier     typescript     rollup     cross-env     karma     karma-chrome-launcher     karma-jasmine     karma-coverage\n#10 CACHED\n\n#11 [7/7] COPY . .\n#11 DONE 0.1s\n\n#12 exporting to image\n#12 exporting layers\n#12 exporting layers 7.6s done\n#12 writing image sha256:8e5c495375b82f51257535f9df6a96b2aad042a105aa9d2c4f1c269fc661ae30 done\n#12 naming to docker.io/library/envgym_test_1756373010 done\n#12 DONE 7.6s\n"
  },
  "run": {
    "success": true,
    "stdout": "",
    "stderr": ""
  }
}