{
  "timestamp": "20250827_214812",
  "dockerfile_path": "envgym/envgym.dockerfile",
  "image_name": "envgym_test_1756331291",
  "build": {
    "success": false,
    "stdout": "",
    "stderr": "#0 building with \"default\" instance using docker driver\n\n#1 [internal] load build definition from envgym.dockerfile\n#1 transferring dockerfile: 1.39kB done\n#1 DONE 0.0s\n\n#2 [internal] load metadata for docker.io/library/ubuntu:22.04\n#2 DONE 0.2s\n\n#3 [internal] load .dockerignore\n#3 transferring context: 2B done\n#3 DONE 0.0s\n\n#4 [ 1/16] FROM docker.io/library/ubuntu:22.04@sha256:1aa979d85661c488ce030ac292876cf6ed04535d3a237e49f61542d8e5de5ae0\n#4 DONE 0.0s\n\n#5 [ 2/16] RUN apt-get update && apt-get install -y     git     build-essential     cmake     libnuma-dev     python3     python3-pip     python3-dev     wget     libaio-dev     libboost-all-dev     libtbb-dev     libgflags-dev     libssl-dev     zlib1g-dev\n#5 CACHED\n\n#6 [ 3/16] RUN mkdir -p /home/cc/EnvGym/data/Baleen\n#6 CACHED\n\n#7 [ 4/16] WORKDIR /home/cc/EnvGym/data/Baleen\n#7 CACHED\n\n#8 [ 5/16] RUN git clone --recurse-submodules https://github.com/wonglkd/Baleen-FAST24.git\n#8 CACHED\n\n#9 [ 6/16] WORKDIR /home/cc/EnvGym/data/Baleen/Baleen-FAST24\n#9 DONE 0.0s\n\n#10 [ 7/16] RUN pip3 install -r requirements.txt\n#10 0.546 ERROR: Could not open requirements file: [Errno 2] No such file or directory: 'requirements.txt'\n#10 ERROR: process \"/bin/sh -c pip3 install -r requirements.txt\" did not complete successfully: exit code: 1\n------\n > [ 7/16] RUN pip3 install -r requirements.txt:\n0.546 ERROR: Could not open requirements file: [Errno 2] No such file or directory: 'requirements.txt'\n------\nenvgym.dockerfile:22\n--------------------\n  20 |     RUN git clone --recurse-submodules https://github.com/wonglkd/Baleen-FAST24.git\n  21 |     WORKDIR /home/cc/EnvGym/data/Baleen/Baleen-FAST24\n  22 | >>> RUN pip3 install -r requirements.txt\n  23 |     RUN pip3 install -e .\n  24 |     WORKDIR /home/cc/EnvGym/data/Baleen/Baleen-FAST24/BCacheSim\n--------------------\nERROR: failed to solve: process \"/bin/sh -c pip3 install -r requirements.txt\" did not complete successfully: exit code: 1\n"
  },
  "run": {
    "success": false,
    "stdout": "",
    "stderr": ""
  }
}